MANIFEST.in
README.txt
setup.cfg
setup.py
authkit/__init__.py
authkit/permissions.py
authkit/request.py
authkit/utils.py
authkit/authenticate/__init__.py
authkit/authenticate/auth_tkt.py
authkit/authenticate/base.py
authkit/authenticate/basic.py
authkit/authenticate/cookie.py
authkit/authenticate/digest.py
authkit/authenticate/form.py
authkit/authenticate/forward.py
authkit/authenticate/multi.py
authkit/authenticate/open_id.py
authkit/authenticate/redirect.py
authkit/authorize/__init__.py
authkit/authorize/decorators.py
authkit/authorize/exc.py
authkit/middleware/__init__.py
authkit/middleware/form.py
authkit/middleware/multi.py
authkit/users/__init__.py
authkit/users/postgresql_driver.py
authkit/users/schevo_04_driver.py
authkit/users/sqlalchemy_04_driver.py
authkit/users/schevo_driver/__init__.py
authkit/users/schevo_driver/model.py
authkit/users/schevo_driver/settings.py
authkit/users/sqlalchemy_driver/__init__.py
authkit/users/sqlalchemy_driver/sqlalchemy_03.py
authkit/users/sqlalchemy_driver/sqlalchemy_04.py
authkit/users/sqlalchemy_driver/sqlalchemy_044.py
authkit/users/sqlalchemy_driver/sqlalchemy_05.py
libauthkit.egg-info/PKG-INFO
libauthkit.egg-info/SOURCES.txt
libauthkit.egg-info/dependency_links.txt
libauthkit.egg-info/entry_points.txt
libauthkit.egg-info/not-zip-safe
libauthkit.egg-info/requires.txt
libauthkit.egg-info/top_level.txt
test/test_base.py
test/test_intercept.py
test/test_multihandler.py
test/test_oauth.py
test/test_schevo_driver.py
test/test_sqlalchemy.py