Metadata-Version: 2.1
Name: libauthkit
Version: 0.5.2
Summary: An extensible authentication and authorization framework on top of WSGI
Home-page: https://www.isotopesoftware.ca/software/libauthkit
Maintainer: Etienne Robillard
Maintainer-email: tkadm30@yandex.com
License: ISC
Platform: UNKNOWN
Provides-Extra: pudge
Provides-Extra: full
